execdata/__init__.py
execdata/eda/__init__.py
execdata/eda/_data_mining.py
execdata/eda/_data_preprocess.py
execdata/eda/_feature_selection.py
execdata/eda/_standardization.py
execdata/format/__init__.py
execdata/format/_data_conversion.py
execdata/format/_format_data.py
execdata/graph/__init__.py
execdata/graph/_data_analysis_graph.py
execdata/graph/_data_mining_graph.py
execdata/graph/_linear_regression_type_graph.py
execdata/graph/_logistic_regression_type_graph.py
execdata/model/__init__.py
execdata/model/_model_evaluate.py
execdata/model/_regression_model.py
execdata-5.5.1.dist-info/LICENSE
execdata-5.5.1.dist-info/METADATA
execdata-5.5.1.dist-info/WHEEL
execdata-5.5.1.dist-info/top_level.txt
execdata-5.5.1.dist-info/RECORD
